Metadata-Version: 2.1
Name: loutils
Version: 1.4.0
Summary: Cross-platform LibreOffice document conversion and printing
Home-page: https://github.com/scivision/libreoffice-utils
Author: Michael Hirsch, Ph.D.
Author-email: scivision@users.noreply.github.com
License: UNKNOWN
Keywords: libreoffice
Platform: UNKNOWN
Classifier: Development Status :: 5 - Production/Stable
Classifier: Environment :: Console
Classifier: Intended Audience :: End Users/Desktop
Classifier: Operating System :: OS Independent
Classifier: Programming Language :: Python :: 3
Classifier: Topic :: Utilities
Requires-Python: >=3.7
Provides-Extra: lint
License-File: LICENSE.txt
